setup.py
distributions/Binomialdistribution.py
distributions/Gaussiandistribution.py
distributions/Generaldistribution.py
distributions/__init__.py
drory_distributions.egg-info/PKG-INFO
drory_distributions.egg-info/SOURCES.txt
drory_distributions.egg-info/dependency_links.txt
drory_distributions.egg-info/not-zip-safe
drory_distributions.egg-info/top_level.txt